animetoolkit/__init__.py
animetoolkit/main.py
animetoolkit-0.0.0.dist-info/LICENSE
animetoolkit-0.0.0.dist-info/METADATA
animetoolkit-0.0.0.dist-info/WHEEL
animetoolkit-0.0.0.dist-info/top_level.txt
animetoolkit-0.0.0.dist-info/RECORD
