Metadata-Version: 2.1
Name: animetoolkit
Version: 0.0.0
Summary: A Python to handle all things anime
Home-page: https://github.com/john-erinjery/animetoolkit/
Author: John Erinjery
Author-email: jancyvinod415@gmail.com
License: MIT
Classifier: Environment :: Console
Classifier: Intended Audience :: Customer Service
Classifier: License :: OSI Approved :: MIT License
Classifier: Natural Language :: English
Classifier: Operating System :: OS Independent
Classifier: Programming Language :: Python :: 3.10
Classifier: Topic :: Internet
Classifier: Topic :: Software Development :: Libraries
Classifier: Topic :: Software Development :: Libraries :: Python Modules
Classifier: Topic :: Utilities
Requires-Python: >=3.10
License-File: LICENSE
